libff/__init__.py
libff/libff.py
libff-0.0.1.dist-info/LICENSE
libff-0.0.1.dist-info/METADATA
libff-0.0.1.dist-info/WHEEL
libff-0.0.1.dist-info/entry_points.txt
libff-0.0.1.dist-info/top_level.txt
libff-0.0.1.dist-info/RECORD
